radar_scenes/__init__.py
radar_scenes/_version.py
radar_scenes/colors.py
radar_scenes/coordinate_transformation.py
radar_scenes/evaluation.py
radar_scenes/labels.py
radar_scenes/scene.py
radar_scenes/sensors.py
radar_scenes/sequence.py
radar_scenes/viewer.py
radar_scenes/examples/__init__.py
radar_scenes/examples/classification.py
radar_scenes/examples/label_statistics.py
radar_scenes/examples/sequences.py
radar_scenes/res/__init__.py
radar_scenes/res/car.png
radar_scenes-1.0.4.dist-info/LICENSE.md
radar_scenes-1.0.4.dist-info/METADATA
radar_scenes-1.0.4.dist-info/WHEEL
radar_scenes-1.0.4.dist-info/entry_points.txt
radar_scenes-1.0.4.dist-info/top_level.txt
radar_scenes-1.0.4.dist-info/RECORD
