Metadata-Version: 2.1
Name: radar_scenes
Version: 1.0.4
Summary: Helper Package for the RadarScenes Dataset
Home-page: https://github.com/oleschum/radar_scenes
Author: Ole Schumann
Author-email: hello@radar-scenes.com
Maintainer: Ole Schumann
Keywords: radar,classification,automotive,machine learning
Classifier: Programming Language :: Python :: 3
Classifier: License :: OSI Approved :: MIT License
Classifier: Operating System :: OS Independent
Requires-Python: >=3.9
License-File: LICENSE.md
Requires-Dist: Pillow >=8.1.0
Requires-Dist: PySide6 >=6.2.2
Requires-Dist: QDarkStyle >=2.8.1
Requires-Dist: h5py >=3.1.0
Requires-Dist: matplotlib >=3.3.3
Requires-Dist: numpy >=1.19.4
Requires-Dist: pip >=19.0.3
Requires-Dist: pyqtgraph >=0.11.1
Requires-Dist: scipy >=1.5.4
Requires-Dist: setuptools >=40.8.0
